root_cause_analyzer/__init__.py
root_cause_analyzer/utils.py
root_cause_analyzer/algorithms/__init__.py
root_cause_analyzer/algorithms/adtributor.py
root_cause_analyzer/algorithms/base_analyzer.py
root_cause_analyzer/config/__init__.py
root_cause_analyzer/config/base_metric_config.py
root_cause_analyzer/config/constants.py
root_cause_analyzer/config/msn_metrics.py
root_cause_analyzer/core/__init__.py
root_cause_analyzer/core/auto_parameter_tuning.py
root_cause_analyzer/core/contribution_calculator.py
root_cause_analyzer/db/__init__.py
root_cause_analyzer/db/azure_db_api.py
root_cause_analyzer/factor_lib/__init__.py
root_cause_analyzer/factor_lib/base_impact_analyzer.py
root_cause_analyzer/factor_lib/experiment_impact.py
root_cause_analyzer/factor_lib/holiday_impact.py
root_cause_analyzer/titan/__init__.py
root_cause_analyzer/titan/titan_api.py
root_cause_analyzer/tools/__init__.py
root_cause_analyzer/tools/business_metrics_analyzer.py
root_cause_analyzer/tools/constants.py
root_cause_analyzer/tools/data_ops.py
root_cause_analyzer/tools/query_utils.py
MSNRootCauseAnalyzer-0.0.8.dist-info/LICENSE
MSNRootCauseAnalyzer-0.0.8.dist-info/METADATA
MSNRootCauseAnalyzer-0.0.8.dist-info/WHEEL
MSNRootCauseAnalyzer-0.0.8.dist-info/top_level.txt
MSNRootCauseAnalyzer-0.0.8.dist-info/RECORD
