Metadata-Version: 2.1
Name: MSNRootCauseAnalyzer
Version: 0.0.8
Summary: A Python library for root cause analysis
Author: MSN CSDATA
Author-email: yankunwang@microsoft.com
Classifier: Programming Language :: Python :: 3
Classifier: License :: OSI Approved :: MIT License
Classifier: Operating System :: OS Independent
Requires-Python: >=3.6
License-File: LICENSE
Requires-Dist: numpy (>=1.21.0)
Requires-Dist: pandas (>=1.3.0)
Requires-Dist: scikit-learn (>=0.24.2)
Requires-Dist: azure-identity (>=1.6.0)
Requires-Dist: msal (>=1.14.0)
Requires-Dist: pyodbc
Requires-Dist: xlsxwriter
